{
    "incident_id": "866aa3a0-0941-11e8-bbae-ed39c73f1398",
    "security_incident": "Confirmed",
    "reference": "https://motherboard.vice.com/en_us/article/hackers-steal-6-million-user-accounts-for-cash-for-surveys-site",
    "summary": "In one of the more bizarre data breaches to surface recently, hackers made off with 6 million accounts for CashCrate, a site where users can be paid to complete online surveys, according to a database obtained by Motherboard.  The data includes user email addresses, names, passwords, and physical addresses.",
    "source_id": "vcdb",
    "confidence": "High",
    "timeline": {
        "incident": {
            "year": 2017,
            "month": 6
        }
    },
    "victim": {
        "victim_id": "CashCrate",
        "employee_count": "Unknown",
        "industry": "561499",
        "country": [
            "Unknown"
        ]
    },
    "action": {
        "hacking": {
            "variety": [
                "Unknown"
            ],
            "vector": [
                "Web application"
            ],
            "result": [
                "Exfiltrate"
            ]
        }
    },
    "actor": {
        "external": {
            "variety": [
                "Unaffiliated"
            ],
            "motive": [
                "Financial"
            ],
            "country": [
                "Unknown"
            ]
        }
    },
    "asset": {
        "assets": [
            {
                "variety": "S - Web application"
            }
        ]
    },
    "attribute": {
        "confidentiality": {
            "data_disclosure": "Yes",
            "data_total": 6000000,
            "data": [
                {
                    "amount": 6000000,
                    "variety": "Personal"
                }
            ],
            "data_victim": [
                "Customer"
            ],
            "state": [
                "Stored"
            ]
        }
    },
    "targeted": "Unknown",
    "discovery_method": "Unknown",
    "plus": {
        "created": "2018-02-04T08:28:50.052Z",
        "modified": "2018-02-04T08:28:50.052Z",
        "master_id": "8df158d9-da04-4d68-936a-4ca0262eae2b",
        "analysis_status": "Validated",
        "analyst": "swidup",
        "dbir_year": 2018,
        "github": "9629"
    },
    "schema_version": "1_3_2"
}