{
  "action": {
    "hacking": {
      "notes": "",
      "variety": [
        "Unknown"
      ],
      "vector": [
        "Unknown"
      ]
    }
  },
  "actor": {
    "external": {
      "country": [
        "Unknown"
      ],
      "motive": [
        "Unknown"
      ],
      "variety": [
        "Unknown"
      ]
    }
  },
  "asset": {
    "assets": [
      {
        "variety": "Unknown"
      }
    ]
  },
  "attribute": {
    "confidentiality": {
      "data": [
        {
          "variety": "Classified"
        },
        {
          "variety": "Personal"
        }
      ],
      "data_disclosure": "Yes",
      "data_total": 31,
      "notes": "Names, addresses, telephone numbers, job titles, and e-mail addresses dumped on the Internet",
      "state": [
        "Stored"
      ]
    }
  },
  "discovery_method": "Unknown",
  "impact": {
    "overall_rating": "Unknown"
  },
  "incident_id": "504800A3-3FAB-4567-A1CE-49C06225F713",
  "notes": "",
  "plus": {
    "analysis_status": "First pass",
    "analyst": "abooker",
    "asset": {
      "total": "No"
    },
    "attribute": {
      "confidentiality": {
        "credit_monitoring": "U",
        "data_abuse": "Y",
        "data_subject": "Partner"
      }
    },
    "created": "2013-02-21T15:01:28Z",
    "f500": "Y",
    "master_id": "504800A3-3FAB-4567-A1CE-49C06225F713",
    "timeline": {
      "notification": {
        "day": 23,
        "month": 3,
        "year": 2012
      }
    }
  },
  "reference": "http://www.efortresses.com/2012-Breaches-Matrix.htm ",
  "schema_version": "1.2",
  "security_incident": "Confirmed",
  "source_id": "vcdb",
  "summary": "Personal information was dumped onto the Internet.  ",
  "timeline": {
    "incident": {
      "year": 2012
    }
  },
  "victim": [
    {
      "country": "US",
      "employee_count": "50001 to 100000",
      "industry": "334511",
      "notes": "",
      "revenue": {
        "amount": 25000000000,
        "iso_currency_code": "USD"
      },
      "state": "Va",
      "victim_id": "Northrop Grumman Systems and Software Engineering Services"
    }
  ]
}