{
  "action": {
    "hacking": {
      "notes": "",
      "variety": [
        "Unknown"
      ],
      "vector": [
        "Unknown"
      ]
    }
  },
  "actor": {
    "external": {
      "country": [
        "Unknown"
      ],
      "motive": [
        "Ideology"
      ],
      "variety": [
        "Activist"
      ]
    }
  },
  "asset": {
    "assets": [
      {
        "variety": "Unknown"
      }
    ]
  },
  "attribute": {
    "confidentiality": {
      "data": [
        {
          "amount": 117,
          "variety": "Personal"
        }
      ],
      "data_disclosure": "Yes",
      "data_total": 117,
      "notes": "",
      "state": [
        "Unknown"
      ]
    }
  },
  "discovery_method": "Unknown",
  "impact": {
    "loss": [
      {
        "rating": "Unknown",
        "variety": "Asset and fraud"
      },
      {
        "rating": "Unknown",
        "variety": "Brand damage"
      },
      {
        "rating": "Unknown",
        "variety": "Business disruption"
      },
      {
        "rating": "Unknown",
        "variety": "Operating costs"
      },
      {
        "rating": "Unknown",
        "variety": "Legal and regulatory"
      },
      {
        "rating": "Unknown",
        "variety": "Competitive advantage"
      },
      {
        "rating": "Unknown",
        "variety": "Response and recovery"
      }
    ],
    "overall_rating": "Unknown"
  },
  "incident_id": "80A9C208-EDFD-4D75-88CD-D1317B507D19",
  "notes": "",
  "plus": {
    "analysis_status": "First pass",
    "analyst": "blackfist",
    "asset": {
      "total": "No"
    },
    "attribute": {
      "confidentiality": {
        "credit_monitoring": "N",
        "data_abuse": "Y",
        "data_subject": "Partner"
      }
    },
    "created": "2013-08-21T14:20:06Z",
    "f500": "N",
    "master_id": "80A9C208-EDFD-4D75-88CD-D1317B507D19",
    "timeline": {
      "notification": {
        "day": 20,
        "month": 8,
        "year": 2013
      }
    }
  },
  "reference": "http://news.softpedia.com/news/OpGabon-Anonymous-Hackers-Leak-Data-from-Gabonese-News-Website-376930.shtml#1750853711264353187(20130821)",
  "schema_version": "1.2",
  "security_incident": "Confirmed",
  "source_id": "vcdb",
  "summary": "Anonymous hackers continue OpGabon. Their latest target is gabonactu.com, a news website that, according to the hackers, is controlled by the Gabonese government. ",
  "timeline": {
    "compromise": {
      "unit": "Unknown"
    },
    "containment": {
      "unit": "Unknown"
    },
    "discovery": {
      "unit": "Unknown"
    },
    "exfiltration": {
      "unit": "Unknown"
    },
    "incident": {
      "year": 2013
    }
  },
  "victim": [
    {
      "country": "GA",
      "employee_count": "Unknown",
      "industry": "51913",
      "notes": "",
      "victim_id": "http://gabonactu.com/"
    }
  ]
}