{
  "action": {
    "hacking": {
      "notes": "",
      "variety": [
        "Unknown"
      ],
      "vector": [
        "Web application"
      ]
    }
  },
  "actor": {
    "external": {
      "country": [
        "SY"
      ],
      "motive": [
        "Ideology"
      ],
      "notes": "Anonymous",
      "variety": [
        "Activist"
      ]
    }
  },
  "asset": {
    "assets": [
      {
        "variety": "S - Web application"
      }
    ]
  },
  "attribute": {
    "integrity": {
      "notes": "",
      "variety": [
        "Modify data",
        "Misappropriation"
      ]
    }
  },
  "discovery_method": "Ext - actor disclosure",
  "impact": {
    "overall_rating": "Unknown"
  },
  "incident_id": "86F23C46-5030-4656-8964-2BA4660C5A58",
  "notes": "",
  "plus": {
    "analyst": "blackfist",
    "created": "2013-10-08T16:12:54Z",
    "f500": "N",
    "github": "410",
    "master_id": "86F23C46-5030-4656-8964-2BA4660C5A58",
    "modified": "2013-12-06T17:29:00Z",
    "timeline": {
      "notification": {
        "day": 30,
        "month": 9,
        "year": 2013
      }
    }
  },
  "reference": "http://news.softpedia.com/news/Hackers-Deface-Ecuador-Government-Site-in-Protest-Against-the-Killing-of-Condors-387162.shtml",
  "schema_version": "1.2.1",
  "security_incident": "Confirmed",
  "source_id": "vcdb",
  "summary": "Hackers from Ecuador have breached and defaced the official website of the government of the province of Azuay (azuay.gob.ec). The hacktivists are protesting against the killing of Andean condors, a protected species in Ecuador.",
  "timeline": {
    "incident": {
      "day": 30,
      "month": 9,
      "year": 2013
    }
  },
  "victim": {
    "country": "EC",
    "employee_count": "Unknown",
    "industry": "921",
    "notes": "",
    "victim_id": "EC Ecuador Province of Azuay"
  }
}