{
  "action": {
    "physical": {
      "location": [
        "Unknown"
      ],
      "variety": [
        "Theft"
      ],
      "vector": [
        "Unknown"
      ]
    }
  },
  "actor": {
    "external": {
      "country": [
        "Unknown"
      ],
      "motive": [
        "Unknown"
      ],
      "variety": [
        "Unknown"
      ]
    }
  },
  "asset": {
    "assets": [
      {
        "variety": "U - Laptop"
      }
    ]
  },
  "attribute": {
    "availability": {
      "variety": [
        "Loss"
      ]
    },
    "confidentiality": {
      "data": [
        {
          "amount": 2739,
          "variety": "Medical"
        }
      ],
      "data_disclosure": "Potentially",
      "data_total": 2739
    }
  },
  "discovery_method": "Unknown",
  "impact": {
    "overall_rating": "Unknown"
  },
  "incident_id": "BC1277FC-D8B2-4EE0-AC0A-803759DA7002",
  "plus": {
    "created": "2013-04-12T22:29:56Z",
    "master_id": "BC1277FC-D8B2-4EE0-AC0A-803759DA7002",
    "timeline": {
      "notification": {}
    }
  },
  "schema_version": "1.2",
  "security_incident": "Confirmed",
  "source_id": "hhs",
  "timeline": {
    "discovery": {
      "unit": "Months",
      "value": 3
    },
    "incident": {
      "day": 20,
      "month": 9,
      "year": 2010
    }
  },
  "victim": [
    {
      "country": "US",
      "employee_count": "1 to 10",
      "industry": "621111",
      "state": "Va",
      "victim_id": "Curtis R. Bryan, MD"
    }
  ]
}