{
  "action": {
    "physical": {
      "location": [
        "Unknown"
      ],
      "variety": [
        "Theft"
      ],
      "vector": [
        "Unknown"
      ]
    }
  },
  "actor": {
    "external": {
      "country": [
        "Unknown"
      ],
      "motive": [
        "Unknown"
      ],
      "variety": [
        "Unknown"
      ]
    }
  },
  "asset": {
    "assets": [
      {
        "variety": "M - Flash drive"
      }
    ]
  },
  "attribute": {
    "availability": {
      "variety": [
        "Loss"
      ]
    },
    "confidentiality": {
      "data": [
        {
          "amount": 705,
          "variety": "Medical"
        }
      ],
      "data_disclosure": "Potentially",
      "data_total": 705
    }
  },
  "discovery_method": "Unknown",
  "impact": {
    "overall_rating": "Unknown"
  },
  "incident_id": "E3B36210-9E12-4F67-B5CF-57880324360E",
  "plus": {
    "analysis_status": "First pass",
    "created": "2013-04-12T22:29:56Z",
    "master_id": "E3B36210-9E12-4F67-B5CF-57880324360E"
  },
  "schema_version": "1.2",
  "security_incident": "Confirmed",
  "source_id": "vcdb",
  "timeline": {
    "discovery": {
      "unit": "Unknown"
    },
    "incident": {
      "day": 28,
      "month": 7,
      "year": 2011
    }
  },
  "victim": [
    {
      "country": "US",
      "employee_count": "1001 to 10000",
      "industry": "524113",
      "state": "Ne",
      "victim_id": "Mutual of Omaha Insurance Company"
    }
  ]
}