{
  "action": {
    "misuse": {
      "variety": [
        "Possession abuse"
      ],
      "vector": [
        "Physical access"
      ]
    }
  },
  "actor": {
    "internal": {
      "motive": [
        "Financial"
      ],
      "variety": [
        "Other"
      ]
    }
  },
  "asset": {
    "assets": [
      {
        "variety": "M - Unknown"
      }
    ],
    "cloud": [
      "Unknown"
    ]
  },
  "attribute": {
    "confidentiality": {
      "data": [
        {
          "variety": "Medical"
        }
      ],
      "data_disclosure": "Yes",
      "data_victim": [
        "Patient"
      ],
      "state": [
        "Unknown"
      ]
    }
  },
  "discovery_method": {
    "internal": {
      "variety": [
        "Fraud detection"
      ]
    }
  },
  "impact": {
    "overall_rating": "Unknown"
  },
  "incident_id": "5A0E29EB-0FBF-4E42-A548-979D97F23768",
  "plus": {
    "analysis_status": "First pass",
    "analyst": "bhaskarvk",
    "attribute": {
      "confidentiality": {
        "credit_monitoring": "Unknown",
        "data_abuse": "Yes"
      }
    },
    "created": "2014-07-10T19:02:00Z",
    "github": "3016",
    "master_id": "5A0E29EB-0FBF-4E42-A548-979D97F23768",
    "modified": "2014-07-10T19:02:00Z",
    "timeline": {
      "notification": {
        "year": 2007
      }
    }
  },
  "reference": "http://www.esecurityplanet.com/network-security/health-care-provider-gets-12-years-in-prison-for-identity-theft.html",
  "schema_version": "1.3.4",
  "security_incident": "Confirmed",
  "source_id": "vcdb",
  "summary": "Victim identities were stolen to submit fraudulent health care claims ",
  "timeline": {
    "incident": {
      "year": 2003
    }
  },
  "victim": {
    "country": [
      "US"
    ],
    "employee_count": "Unknown",
    "industry": "000",
    "region": [
      "019021"
    ],
    "secondary": {
      "amount": 1,
      "notes": "Ended up paying millions of dollars on false claims",
      "victim_id": [
        "Medicare"
      ]
    }
  }
}