{
  "action": {
    "hacking": {
      "variety": [
        "Unknown"
      ],
      "vector": [
        "Web application"
      ]
    }
  },
  "actor": {
    "external": {
      "country": [
        "AR"
      ],
      "motive": [
        "Ideology"
      ],
      "region": [
        "019005"
      ],
      "variety": [
        "Activist"
      ]
    }
  },
  "asset": {
    "assets": [
      {
        "variety": "S - Web application"
      }
    ],
    "cloud": [
      "Unknown"
    ]
  },
  "attribute": {
    "integrity": {
      "variety": [
        "Modify data",
        "Repurpose"
      ]
    }
  },
  "discovery_method": {
    "external": {
      "variety": [
        "Actor disclosure"
      ]
    }
  },
  "incident_id": "7124DCE6-7EFC-41A6-B42A-327AB259F76B",
  "plus": {
    "analysis_status": "First pass",
    "analyst": "blackfist",
    "created": "2013-12-30T22:04:23Z",
    "github": "950",
    "master_id": "7124DCE6-7EFC-41A6-B42A-327AB259F76B",
    "modified": "2014-04-27T19:37:02Z",
    "timeline": {
      "notification": {
        "day": 2,
        "month": 12,
        "year": 2013
      }
    }
  },
  "reference": "http://www.ehackingnews.com/2013/11/union-of-reserve-officers-of-armed.html (20131230);http://news.softpedia.com/news/Anonymous-Hackers-Deface-Venezuelan-Government-Websites-405222.shtml (20131230)",
  "schema_version": "1.3.4",
  "security_incident": "Confirmed",
  "source_id": "vcdb",
  "summary": "Last week, the Argentinian hackers defaced a website belonging to Argentinas military. They claim they havent deleted any important data. Instead, they simply wanted to show that security doesnt exist in Argentina.",
  "timeline": {
    "incident": {
      "year": 2013
    }
  },
  "victim": {
    "country": [
      "AR"
    ],
    "employee_count": "Unknown",
    "industry": "928110",
    "region": [
      "019005"
    ],
    "victim_id": "AR Argentina Military"
  }
}