{
  "action": {
    "physical": {
      "variety": [
        "Theft"
      ],
      "vector": [
        "Partner facility"
      ]
    }
  },
  "actor": {
    "external": {
      "country": [
        "Unknown"
      ],
      "motive": [
        "Financial"
      ],
      "region": [
        "000000"
      ],
      "variety": [
        "Unknown"
      ]
    }
  },
  "asset": {
    "assets": [
      {
        "variety": "U - Laptop"
      },
      {
        "variety": "U - Desktop or laptop"
      }
    ],
    "cloud": [
      "Unknown"
    ]
  },
  "attribute": {
    "availability": {
      "variety": [
        "Loss"
      ]
    },
    "confidentiality": {
      "data": [
        {
          "variety": "Personal"
        }
      ],
      "data_disclosure": "Potentially",
      "data_victim": [
        "Customer"
      ],
      "state": [
        "Stored unencrypted"
      ]
    }
  },
  "discovery_method": {
    "internal": {
      "variety": [
        "Reported by employee"
      ]
    }
  },
  "impact": {
    "overall_rating": "Unknown"
  },
  "incident_id": "A709F818-004D-4388-BF34-5939CDDB32BE",
  "notes": "Second pass completed 1/9/16 STW.",
  "plus": {
    "analysis_status": "Finalized",
    "analyst": "jesse.moody@my.southcentral.edu",
    "attribute": {
      "confidentiality": {
        "credit_monitoring": "Unknown"
      }
    },
    "created": "2015-04-30T01:32:00Z",
    "dbir_year": 2016,
    "github": "4980",
    "master_id": "A709F818-004D-4388-BF34-5939CDDB32BE",
    "modified": "2015-04-30T01:32:00Z",
    "timeline": {
      "notification": {
        "year": 2014
      }
    }
  },
  "reference": "http://www.scmagazine.com/stolen-emcor-services-laptop-contained-social-security-numbers-other-data/article/388422/; http://oag.ca.gov/system/files/Breach%20letter%20final%2012%2011%2014_0.pdf?",
  "schema_version": "1.3.4",
  "security_incident": "Confirmed",
  "source_id": "vcdb",
  "summary": "Stolen EMCOR Services laptop contained Social Security numbers, other data.  Names, addresses, genders, ethnicities, dates of birth, dates of hire, salaries and Social Security numbers.",
  "timeline": {
    "incident": {
      "day": 25,
      "month": 11,
      "year": 2014
    }
  },
  "victim": {
    "country": [
      "US"
    ],
    "employee_count": "25001 to 50000",
    "industry": "238220",
    "locations_affected": 1,
    "region": [
      "019021"
    ],
    "state": "CA",
    "victim_id": "EMCOR Services"
  }
}