{
  "action": {
    "error": {
      "variety": [
        "Misdelivery"
      ],
      "vector": [
        "Carelessness"
      ]
    }
  },
  "actor": {
    "internal": {
      "motive": [
        "NA"
      ],
      "variety": [
        "Unknown"
      ]
    }
  },
  "asset": {
    "assets": [
      {
        "variety": "M - Documents"
      }
    ],
    "cloud": [
      "Unknown"
    ]
  },
  "attribute": {
    "confidentiality": {
      "data": [
        {
          "variety": "Personal"
        }
      ],
      "data_disclosure": "Yes"
    }
  },
  "discovery_method": {
    "unknown": true
  },
  "incident_id": "B671EDAB-62A0-11E3-BC5D-14109FCE954D",
  "plus": {
    "analysis_status": "First pass",
    "analyst": "swidup",
    "created": "2013-12-11T20:13:34Z",
    "master_id": "B671EDAB-62A0-11E3-BC5D-14109FCE954D",
    "modified": "2014-07-30T19:07:18Z"
  },
  "reference": "http://vcdb.org/pdf/va-security.pdf",
  "schema_version": "1.3.4",
  "security_incident": "Confirmed",
  "source_id": "vcdb",
  "summary": "Employee self reported that she had processed an Advance Directive with the wrong Veteran identifiers. Veteran As information was on the form. Veteran B signed the form thinking it was his. Veteran B was asked to return the Advance Directive. Only the headers on continuation pages had the wrong Veteran's name and full SSN",
  "timeline": {
    "incident": {
      "year": 2013
    }
  },
  "victim": {
    "country": [
      "US"
    ],
    "employee_count": "Unknown",
    "industry": "923140",
    "region": [
      "019021"
    ],
    "state": "RI",
    "victim_id": "United States Department of Veterans Affairs"
  }
}