{
  "action": {
    "error": {
      "notes": "The notes of three other patients were in the file of the person who complained deceased mother. ",
      "variety": [
        "Disposal error"
      ],
      "vector": [
        "Carelessness"
      ]
    }
  },
  "actor": {
    "internal": {
      "motive": [
        "NA"
      ],
      "variety": [
        "Unknown",
        "End-user"
      ]
    }
  },
  "asset": {
    "assets": [
      {
        "variety": "M - Documents"
      }
    ],
    "cloud": [
      "Unknown"
    ]
  },
  "attribute": {
    "confidentiality": {
      "data": [
        {
          "amount": 3,
          "variety": "Medical"
        }
      ],
      "data_disclosure": "Yes",
      "data_total": 3,
      "data_victim": [
        "Patient"
      ],
      "state": [
        "Unknown"
      ]
    }
  },
  "discovery_method": {
    "external": {
      "variety": [
        "Customer"
      ]
    }
  },
  "impact": {
    "overall_rating": "Unknown"
  },
  "incident_id": "48810C37-AB47-4E5D-917D-5FFA30FD4597",
  "plus": {
    "analysis_status": "Finalized",
    "analyst": "DaveyBaby",
    "attribute": {
      "confidentiality": {
        "credit_monitoring": "Unknown"
      }
    },
    "created": "2016-09-13T15:42:00Z",
    "dbir_year": 2017,
    "github": "5473",
    "master_id": "D418DF86-23DE-45AF-A114-72B205FFE0A3",
    "modified": "2016-09-13T15:58:00Z",
    "sub_source": "phidbr",
    "timeline": {
      "notification": {
        "day": 15,
        "month": 11,
        "year": 2015
      }
    }
  },
  "reference": "http://www.abc.net.au/news/2015-03-02/patient-seeks-answers-after-confidential-medical-records-leaked/6274944",
  "schema_version": "1.3.4",
  "security_incident": "Confirmed",
  "source_id": "vcdb",
  "summary": "SA Health is investigating how confidential medical notes from three Lyell McEwin Hospital patients in Adelaide ended up in someone else's file.",
  "timeline": {
    "incident": {
      "year": 2015
    }
  },
  "victim": {
    "country": [
      "AU"
    ],
    "employee_count": "Unknown",
    "industry": "620111",
    "region": [
      "009053"
    ],
    "victim_id": "Lyell McEwin Hospital"
  }
}