{
  "action": {
    "hacking": {
      "variety": [
        "SQLi",
        "Exploit vuln"
      ],
      "vector": [
        "Web application"
      ]
    }
  },
  "actor": {
    "external": {
      "country": [
        "Unknown"
      ],
      "motive": [
        "Fun",
        "Unknown"
      ],
      "region": [
        "000000"
      ],
      "variety": [
        "Unknown",
        "Unaffiliated"
      ]
    }
  },
  "asset": {
    "assets": [
      {
        "variety": "S - Database"
      }
    ],
    "cloud": [
      "Unknown"
    ]
  },
  "attribute": {
    "confidentiality": {
      "data": [
        {
          "amount": 2200000,
          "variety": "Credentials"
        }
      ],
      "data_disclosure": "Yes",
      "data_total": 2200000,
      "data_victim": [
        "Customer"
      ],
      "state": [
        "Stored unencrypted"
      ]
    },
    "integrity": {
      "variety": [
        "Repurpose"
      ]
    }
  },
  "discovery_method": {
    "external": {
      "variety": [
        "Actor disclosure"
      ]
    }
  },
  "impact": {
    "overall_rating": "Unknown"
  },
  "incident_id": "796F6440-4F21-42E9-A15A-71E0D9F97456",
  "plus": {
    "analysis_status": "Finalized",
    "analyst": "Spitler",
    "attribute": {
      "confidentiality": {
        "credit_monitoring": "Unknown"
      }
    },
    "created": "2017-01-27T19:50:00Z",
    "dbir_year": 2017,
    "github": "8514",
    "master_id": "D42BACD9-B649-4B32-B418-F37CCA409FB9",
    "modified": "2017-01-27T19:58:00Z",
    "sub_source": "priority",
    "timeline": {
      "notification": {
        "month": 10,
        "year": 2016
      }
    }
  },
  "reference": "http://arstechnica.com/security/2016/09/social-hangout-site-for-teens-leaks-millions-of-plaintext-passwords/",
  "schema_version": "1.3.4",
  "security_incident": "Confirmed",
  "source_id": "vcdb",
  "summary": "SQLi leads to database compromise of 5.5 million credentials to teen social site",
  "timeline": {
    "compromise": {
      "unit": "Days"
    },
    "discovery": {
      "unit": "Weeks"
    },
    "incident": {
      "month": 6,
      "year": 2016
    }
  },
  "victim": {
    "country": [
      "US"
    ],
    "employee_count": "Small",
    "industry": "519130",
    "region": [
      "019021"
    ],
    "state": "CA",
    "victim_id": "i-Dressup"
  }
}