{
  "action": {
    "misuse": {
      "variety": [
        "Possession abuse"
      ],
      "vector": [
        "Physical access"
      ]
    }
  },
  "actor": {
    "internal": {
      "job_change": [
        "Hired"
      ],
      "motive": [
        "Unknown",
        "Financial"
      ],
      "variety": [
        "Unknown",
        "Other"
      ]
    },
    "partner": {
      "country": [
        "Unknown"
      ],
      "industry": "000",
      "motive": [
        "Unknown"
      ],
      "region": [
        "000000"
      ]
    }
  },
  "asset": {
    "assets": [
      {
        "variety": "S - Database"
      }
    ],
    "cloud": [
      "Unknown"
    ],
    "notes": "Preliminary findings indicate the former contractor may have copied these agent files. The files accessed contained names "
  },
  "attribute": {
    "confidentiality": {
      "data": [
        {
          "variety": "Personal"
        }
      ],
      "data_disclosure": "Yes",
      "data_victim": [
        "Partner"
      ],
      "state": [
        "Stored"
      ]
    }
  },
  "discovery_method": {
    "unknown": true
  },
  "discovery_notes": "While an investigation continues, it is unclear at this time how or if the personal agent data was used. Out of an abundance of caution, this notification is being made by the Commission.",
  "impact": {
    "overall_rating": "Unknown"
  },
  "incident_id": "B69EE252-E06A-4776-8B3F-22E3BA3B9736",
  "plus": {
    "analysis_status": "Finalized",
    "analyst": "Robert-Topper",
    "attribute": {
      "confidentiality": {
        "credit_monitoring": "Unknown",
        "data_abuse": "Yes"
      }
    },
    "created": "2016-09-27T14:05:00Z",
    "dbir_year": 2016,
    "github": "7907",
    "master_id": "E5B4B79B-2FC4-426A-B7EF-9B64DBA69D20",
    "modified": "2016-09-27T14:10:00Z",
    "timeline": {
      "notification": {
        "day": 10,
        "month": 6,
        "year": 2015
      }
    }
  },
  "reference": "http://augustafreepress.com/scc-advises-former-licensed-insurance-agents-possible-data-breach/; http://pilotonline.com/business/insurance-agents-in-virginia-may-have-had-personal-data-stolen/article_c8052cf4-513f-561d-8407-9deb69210bc8.html",
  "schema_version": "1.3.4",
  "security_incident": "Confirmed",
  "source_id": "vcdb",
  "summary": "State Corporation Commission is advising former licensed insurance agents of the potential improper access to their personal data by a former contractor",
  "timeline": {
    "incident": {
      "month": 6,
      "year": 2015
    }
  },
  "victim": {
    "country": [
      "US"
    ],
    "employee_count": "11 to 100",
    "industry": "92",
    "locations_affected": 1,
    "region": [
      "019021"
    ],
    "state": "VA",
    "victim_id": "Virginia's State Corporation Commission"
  }
}