{
  "action": {
    "error": {
      "variety": [
        "Disposal error"
      ],
      "vector": [
        "Unknown"
      ]
    }
  },
  "actor": {
    "internal": {
      "motive": [
        "NA"
      ],
      "variety": [
        "Unknown"
      ]
    }
  },
  "asset": {
    "assets": [
      {
        "variety": "M - Disk drive"
      }
    ],
    "cloud": [
      "Unknown"
    ]
  },
  "attribute": {
    "confidentiality": {
      "data": [
        {
          "variety": "Medical"
        }
      ],
      "data_disclosure": "Potentially",
      "data_victim": [
        "Customer"
      ],
      "state": [
        "Stored unencrypted"
      ]
    }
  },
  "discovery_method": {
    "internal": {
      "variety": [
        "Unknown"
      ]
    }
  },
  "impact": {
    "overall_rating": "Unknown"
  },
  "incident_id": "E9EDF8A8-35D0-4D22-8538-0E044A55DABA",
  "plus": {
    "analysis_status": "Finalized",
    "analyst": "Spitler",
    "attribute": {
      "confidentiality": {
        "credit_monitoring": "Unknown"
      }
    },
    "created": "2016-08-18T15:27:00Z",
    "dbir_year": 2017,
    "github": "7160",
    "master_id": "EF05B42B-82C2-4077-8958-D7EC083121F0",
    "modified": "2016-08-18T15:32:00Z",
    "sub_source": "phidbr",
    "timeline": {
      "notification": {
        "day": 4,
        "month": 2,
        "year": 2016
      }
    }
  },
  "reference": "http://www.desmoinesregister.com/story/tech/2016/02/04/medicap-pharmacy-warns-possible-data-breach/79820534/",
  "schema_version": "1.3.4",
  "security_incident": "Confirmed",
  "source_id": "vcdb",
  "summary": "Disposal error of hard drive.",
  "timeline": {
    "incident": {
      "day": 5,
      "month": 11,
      "year": 2015
    }
  },
  "victim": {
    "country": [
      "US"
    ],
    "employee_count": "11 to 100",
    "industry": "446110",
    "region": [
      "019021"
    ],
    "state": "IA",
    "victim_id": "Medicap Pharmacy"
  }
}